<?xml version="1.0" encoding="UTF-16"?>
<TextureAtlas imagePath="gm.png">
	<!-- Created with Adobe Flash CS6 version 12.0.0.481 -->
	<!-- http://www.adobe.com/products/flash.html -->
	<SubTexture name="game over confirm0000" x="0" y="0" width="973" height="366"/>
	<SubTexture name="game over confirm0001" x="0" y="0" width="973" height="366"/>
	<SubTexture name="game over confirm0002" x="0" y="0" width="973" height="366"/>
	<SubTexture name="game over confirm0003" x="0" y="0" width="973" height="366"/>
	<SubTexture name="game over confirm0004" x="0" y="0" width="973" height="366"/>
	<SubTexture name="game over confirm0005" x="0" y="0" width="973" height="366"/>
	<SubTexture name="game over confirm0006" x="0" y="0" width="973" height="366"/>
	<SubTexture name="game over confirm0007" x="0" y="0" width="973" height="366"/>
	<SubTexture name="game over confirm0008" x="0" y="0" width="973" height="366"/>
	<SubTexture name="game over confirm0009" x="0" y="0" width="973" height="366"/>
	<SubTexture name="game over confirm0010" x="0" y="0" width="973" height="366"/>
	<SubTexture name="game over confirm0011" x="0" y="0" width="973" height="366"/>
	<SubTexture name="game over confirm0012" x="0" y="0" width="973" height="366"/>
	<SubTexture name="game over confirm0013" x="0" y="0" width="973" height="366"/>
	<SubTexture name="game over confirm0014" x="0" y="0" width="973" height="366"/>
	<SubTexture name="game over confirm0015" x="0" y="0" width="973" height="366"/>
	<SubTexture name="game over confirm0016" x="0" y="0" width="973" height="366"/>
	<SubTexture name="game over confirm0017" x="0" y="0" width="973" height="366"/>
	<SubTexture name="game over confirm0018" x="0" y="0" width="973" height="366"/>
	<SubTexture name="game over confirm0019" x="0" y="0" width="973" height="366"/>
	<SubTexture name="game over death0000" x="973" y="0" width="991" height="469"/>
	<SubTexture name="game over death0001" x="973" y="0" width="991" height="469"/>
	<SubTexture name="game over death0002" x="0" y="469" width="991" height="469"/>
	<SubTexture name="game over death0003" x="0" y="469" width="991" height="469"/>
	<SubTexture name="game over death0004" x="991" y="469" width="991" height="469"/>
	<SubTexture name="game over death0005" x="991" y="469" width="991" height="469"/>
	<SubTexture name="game over death0006" x="0" y="938" width="991" height="469"/>
	<SubTexture name="game over death0007" x="0" y="938" width="991" height="469"/>
	<SubTexture name="game over death0008" x="991" y="938" width="991" height="469"/>
	<SubTexture name="game over death0009" x="991" y="938" width="991" height="469"/>
	<SubTexture name="game over death0010" x="0" y="1407" width="991" height="469"/>
	<SubTexture name="game over death0011" x="0" y="1407" width="991" height="469"/>
	<SubTexture name="game over death0012" x="991" y="1407" width="991" height="469"/>
	<SubTexture name="game over death0013" x="991" y="1407" width="991" height="469"/>
	<SubTexture name="game over death0014" x="0" y="1876" width="991" height="469"/>
	<SubTexture name="game over death0015" x="0" y="1876" width="991" height="469"/>
	<SubTexture name="game over death0016" x="991" y="1876" width="991" height="469"/>
	<SubTexture name="game over death0017" x="991" y="1876" width="991" height="469"/>
	<SubTexture name="game over death0018" x="0" y="2345" width="991" height="469"/>
	<SubTexture name="game over death0019" x="0" y="2345" width="991" height="469"/>
	<SubTexture name="game over death0020" x="0" y="2345" width="991" height="469"/>
	<SubTexture name="game over death0021" x="0" y="2345" width="991" height="469"/>
	<SubTexture name="game over death0022" x="0" y="2345" width="991" height="469"/>
	<SubTexture name="game over death0023" x="0" y="2345" width="991" height="469"/>
	<SubTexture name="game over death0024" x="0" y="2345" width="991" height="469"/>
	<SubTexture name="game over death0025" x="0" y="2345" width="991" height="469"/>
	<SubTexture name="game over death0026" x="0" y="2345" width="991" height="469"/>
	<SubTexture name="game over death0027" x="0" y="2345" width="991" height="469"/>
	<SubTexture name="game over death0028" x="0" y="2345" width="991" height="469"/>
	<SubTexture name="game over death0029" x="0" y="2345" width="991" height="469"/>
	<SubTexture name="game over death0030" x="0" y="2345" width="991" height="469"/>
	<SubTexture name="game over death0031" x="0" y="2345" width="991" height="469"/>
	<SubTexture name="game over death0032" x="0" y="2345" width="991" height="469"/>
	<SubTexture name="game over death0033" x="0" y="2345" width="991" height="469"/>
	<SubTexture name="game over death0034" x="0" y="2345" width="991" height="469"/>
	<SubTexture name="game over death0035" x="0" y="2345" width="991" height="469"/>
	<SubTexture name="game over death0036" x="0" y="2345" width="991" height="469"/>
	<SubTexture name="game over loop0000" x="991" y="2345" width="980" height="366"/>
	<SubTexture name="game over loop0001" x="991" y="2345" width="980" height="366"/>
	<SubTexture name="game over loop0002" x="991" y="2345" width="980" height="366"/>
	<SubTexture name="game over loop0003" x="991" y="2345" width="980" height="366"/>
	<SubTexture name="game over loop0004" x="991" y="2345" width="980" height="366"/>
	<SubTexture name="game over loop0005" x="991" y="2345" width="980" height="366"/>
	<SubTexture name="game over loop0006" x="991" y="2345" width="980" height="366"/>
	<SubTexture name="game over loop0007" x="991" y="2345" width="980" height="366"/>
	<SubTexture name="game over loop0008" x="991" y="2345" width="980" height="366"/>
	<SubTexture name="game over loop0009" x="0" y="2814" width="980" height="366"/>
	<SubTexture name="game over loop0010" x="0" y="2814" width="980" height="366"/>
	<SubTexture name="game over loop0011" x="980" y="2814" width="980" height="366"/>
	<SubTexture name="game over loop0012" x="980" y="2814" width="980" height="366"/>
	<SubTexture name="game over loop0013" x="991" y="2345" width="980" height="366"/>
	<SubTexture name="game over loop0014" x="991" y="2345" width="980" height="366"/>
	<SubTexture name="game over loop0015" x="991" y="2345" width="980" height="366"/>
	<SubTexture name="game over loop0016" x="991" y="2345" width="980" height="366"/>
	<SubTexture name="game over loop0017" x="991" y="2345" width="980" height="366"/>
	<SubTexture name="game over loop0018" x="991" y="2345" width="980" height="366"/>
	<SubTexture name="game over loop0019" x="991" y="2345" width="980" height="366"/>
</TextureAtlas>
